edamame/__init__.py
edamame/classifier/__init__.py
edamame/classifier/classification.py
edamame/classifier/diagnose.py
edamame/eda/__init__.py
edamame/eda/eda.py
edamame/eda/tools.py
edamame/regressor/__init__.py
edamame/regressor/diagnose.py
edamame/regressor/regression.py
edamame-0.59.dist-info/LICENSE
edamame-0.59.dist-info/METADATA
edamame-0.59.dist-info/WHEEL
edamame-0.59.dist-info/top_level.txt
edamame-0.59.dist-info/RECORD
