Metadata-Version: 2.1
Name: edamame
Version: 0.59
Summary: Exploratory data analysis tools
Author-email: Marco Salvalaggio <mar.salvalaggio@gmail.com>
License: Copyright (c) 2018 The Python Packaging Authority
Project-URL: Homepage, https://github.com/marcosalvalaggio/edamame
Project-URL: Bug Tracker, https://github.com/marcosalvalaggio/edamame/issues
Classifier: Programming Language :: Python :: 3
Classifier: License :: OSI Approved :: MIT License
Classifier: Operating System :: OS Independent
Requires-Python: >=3.7
License-File: LICENSE
Requires-Dist: pandas
Requires-Dist: numpy
Requires-Dist: scikit-learn
Requires-Dist: ipython
Requires-Dist: matplotlib
Requires-Dist: seaborn
Requires-Dist: scipy
Requires-Dist: phik
Requires-Dist: ipywidgets
Requires-Dist: xgboost
